depsgraph/__init__.py
depsgraph/__main__.py
depsgraph-0.1.4.dist-info/METADATA
depsgraph-0.1.4.dist-info/WHEEL
depsgraph-0.1.4.dist-info/top_level.txt
depsgraph-0.1.4.dist-info/RECORD
