Metadata-Version: 2.4
Name: depsgraph
Version: 0.1.4
Summary: Visualize internal Python import dependencies
Requires-Python: >=3.11
Requires-Dist: build>=1.4.0
Requires-Dist: twine>=6.2.0
